sv_converter/__init__.py
sv_converter/density.py
sv_converter/length.py
sv_converter/mass.py
sv_converter/utils.py
sv_converter/volume.py
sv_converter-0.1.0.dist-info/METADATA
sv_converter-0.1.0.dist-info/WHEEL
sv_converter-0.1.0.dist-info/top_level.txt
sv_converter-0.1.0.dist-info/RECORD
