Metadata-Version: 2.1
Name: sv-converter
Version: 0.1.0
Summary: Easily convert values of different units of measurement.
Home-page: https://github.com/ihavenonickname/sv-converter
Author: Gabriel Blank Stift Mousquer
Author-email: gabrielblanksm@gmail.com
License: MIT
Platform: UNKNOWN
